red/__init__.py
red/blueprint.py
red/metrics.py
red/tracker.py
RED_Metrics_Tracker-0.1.1.dist-info/LICENSE
RED_Metrics_Tracker-0.1.1.dist-info/WHEEL
RED_Metrics_Tracker-0.1.1.dist-info/METADATA
RED_Metrics_Tracker-0.1.1.dist-info/RECORD
