Metadata-Version: 2.1
Name: RED-Metrics-Tracker
Version: 0.1.1
Summary: RED Metrics tracker able to instrument flask views using prometheus metrics.
Home-page: https://github.com/nlsdfnbch/RED-Metrics-Tracker
License: UNKNOWN
Keywords: red-metrics, prometheus, instrumentation, metrics
Author: Nils Diefenbach
Author-email: nlsdfnbch.foos@kolabnow.com
Requires-Python: >3.6
Classifier: Intended Audience :: Developers
Classifier: Intended Audience :: Information Technology
Classifier: License :: OSI Approved :: MIT License
Classifier: Programming Language :: Python :: 3 :: Only
Classifier: Programming Language :: Python :: Implementation :: CPython
Requires-Dist: prometheus_client
Requires-Dist: flask
Requires-Dist: black==19.3b0; extra == "dev"
Requires-Dist: flake8-bugbear==18.8.0; extra == "dev"
Requires-Dist: flake8-tuple==0.2.13; extra == "dev"
Requires-Dist: flake8==3.7.5; extra == "dev"
Requires-Dist: isort==4.3.16; extra == "dev"
Requires-Dist: pytest==4.5.0; extra == "dev"
Requires-Dist: pytest; extra == "test"
Project-URL: Bug Tracker, https://github.com/nlsdfnbch/RED-Metrics-Tracker/issues
Project-URL: GitHub, https://github.com/nlsdfnbch/RED-Metrics-Tracker
Provides-Extra: dev
Provides-Extra: test
